knnclassifier/__init__.py
knnclassifier/knn_module.py
knnclassifier-1.0.0.dist-info/METADATA
knnclassifier-1.0.0.dist-info/WHEEL
knnclassifier-1.0.0.dist-info/licenses/LICENSE
knnclassifier-1.0.0.dist-info/RECORD
