Metadata-Version: 2.3
Name: knnclassifier
Version: 1.0.0
Summary: A k-nearest neighbors classifier in Python 3.11.7
Project-URL: Homepage, https://github.com/justinroche/knnclassifier
Project-URL: Issues, https://github.com/justinroche/knnclassifier/issues
Author-email: Justin Roche <justinroche03@gmail.com>
License-File: LICENSE
Classifier: License :: OSI Approved :: MIT License
Classifier: Operating System :: OS Independent
Classifier: Programming Language :: Python :: 3
Requires-Python: >=3.8
Requires-Dist: numpy>=1.23.5
